wolt_test_package/__init__.py
wolt_test_package-0.1.0.dist-info/METADATA
wolt_test_package-0.1.0.dist-info/WHEEL
wolt_test_package-0.1.0.dist-info/RECORD
